shemic/__init__.py
shemic-1.0.0.dist-info/LICENSE
shemic-1.0.0.dist-info/METADATA
shemic-1.0.0.dist-info/WHEEL
shemic-1.0.0.dist-info/top_level.txt
shemic-1.0.0.dist-info/RECORD
