Metadata-Version: 2.1
Name: shemic
Version: 1.0.0
Summary: Shemic Lab
Author-email: rabin <2934170@qq.com>
Project-URL: Homepage, https://github.com/shemic/
Project-URL: Bug Tracker, https://github.com/shemic/
Classifier: Programming Language :: Python :: 3
Classifier: License :: OSI Approved :: MIT License
Classifier: Operating System :: OS Independent
Requires-Python: >=3.7
License-File: LICENSE
